service_person_stamdata_udvidet/PersonBaseDataExtended_v4_envelope.xml
service_person_stamdata_udvidet/PersonBaseDataExtended_v5_envelope.xml
service_person_stamdata_udvidet/__init__.py
service_person_stamdata_udvidet/helpers.py
service_person_stamdata_udvidet/udvidet_person_stam_data_lokal.py
service_person_stamdata_udvidet-1.0.3.dist-info/LICENSE
service_person_stamdata_udvidet-1.0.3.dist-info/METADATA
service_person_stamdata_udvidet-1.0.3.dist-info/WHEEL
service_person_stamdata_udvidet-1.0.3.dist-info/top_level.txt
service_person_stamdata_udvidet-1.0.3.dist-info/RECORD
